dashmips/__init__.py
dashmips/__main__.py
dashmips/debugger.py
dashmips/debuggerserver.py
dashmips/directives.py
dashmips/extension.py
dashmips/hardware.py
dashmips/instructions/Instruction.py
dashmips/instructions/__init__.py
dashmips/instructions/imm_instructions.py
dashmips/instructions/pseudo_instructions.py
dashmips/instructions/rd_imm_instructions.py
dashmips/instructions/rd_instructions.py
dashmips/instructions/rd_rs_lbl_instructions.py
dashmips/instructions/rd_rs_rt_instructions.py
dashmips/instructions/rs_imm_instructions.py
dashmips/instructions/rs_instructions.py
dashmips/instructions/rs_mem_instructions.py
dashmips/instructions/rs_rt_imm_instructions.py
dashmips/instructions/rs_rt_instructions.py
dashmips/instructions/special_instructions.py
dashmips/mips.py
dashmips/models.py
dashmips/plugins/__init__.py
dashmips/plugins/vt100.py
dashmips/preprocessor.py
dashmips/run.py
dashmips/syscalls/Syscall.py
dashmips/syscalls/__init__.py
dashmips/syscalls/file_syscalls.py
dashmips/syscalls/print_syscalls.py
dashmips/syscalls/process_syscalls.py
dashmips/syscalls/read_syscalls.py
dashmips/utils.py
dashmips/visualize.py
dashmips-0.1.10.dist-info/entry_points.txt
dashmips-0.1.10.dist-info/LICENSE
dashmips-0.1.10.dist-info/WHEEL
dashmips-0.1.10.dist-info/METADATA
dashmips-0.1.10.dist-info/RECORD
